pytest_vscode_pycharm_cls/__init__.py
pytest_vscode_pycharm_cls/pytest_integration.py
pytest_vscode_pycharm_cls-0.6.dist-info/LICENSE
pytest_vscode_pycharm_cls-0.6.dist-info/METADATA
pytest_vscode_pycharm_cls-0.6.dist-info/WHEEL
pytest_vscode_pycharm_cls-0.6.dist-info/entry_points.txt
pytest_vscode_pycharm_cls-0.6.dist-info/top_level.txt
pytest_vscode_pycharm_cls-0.6.dist-info/RECORD
